mysql_api/__init__.py
mysql_api/exception.py
mysql_api/mysql_database.py
mysql_api-1.11.0.dist-info/METADATA
mysql_api-1.11.0.dist-info/WHEEL
mysql_api-1.11.0.dist-info/RECORD
