Metadata-Version: 2.4
Name: mysql-api
Version: 1.11.0
Summary: 封装mysql操作
Author: LiuWei
Author-email: 183074632@qq.com
Requires-Python: >=3.11,<4.0
Classifier: Programming Language :: Python :: 3
Classifier: Programming Language :: Python :: 3.11
Classifier: Programming Language :: Python :: 3.12
Classifier: Programming Language :: Python :: 3.13
Classifier: Programming Language :: Python :: 3.14
Requires-Dist: cryptography (>=44.0.0,<45.0.0)
Requires-Dist: pymysql (>=1.1.1,<2.0.0)
Requires-Dist: sqlalchemy (>=2.0.36,<3.0.0)
